maic/__init__.py
maic/assertion.py
maic/constants.py
maic/decorators.py
maic/testrunner.py
maic/utils.py
maic/database/__init__.py
maic/database/store.py
maic-0.0.1.dev3.dist-info/DESCRIPTION.rst
maic-0.0.1.dev3.dist-info/METADATA
maic-0.0.1.dev3.dist-info/RECORD
maic-0.0.1.dev3.dist-info/WHEEL
maic-0.0.1.dev3.dist-info/metadata.json
maic-0.0.1.dev3.dist-info/top_level.txt
